leximpact_survey_scenario/__init__.py
leximpact_survey_scenario/graphiques_cas_type/__init__.py
leximpact_survey_scenario/graphiques_cas_type/base.py
leximpact_survey_scenario/graphiques_cas_type/cas_type_general.ipynb
leximpact_survey_scenario/graphiques_cas_type/cas_type_prestations_familiales.ipynb
leximpact_survey_scenario/graphiques_cas_type/cas_type_utils.py
leximpact_survey_scenario/graphiques_cas_type/decomposition.py
leximpact_survey_scenario/graphiques_cas_type/gain_enfants.py
leximpact_survey_scenario/graphiques_cas_type/utils.py
leximpact_survey_scenario/leximpact_survey_scenario.py
leximpact_survey_scenario/leximpact_tax_and_benefit_system.py
leximpact_survey_scenario/scenario_tools/__init__.py
leximpact_survey_scenario/scenario_tools/calage_tax_benefits_system.py
leximpact_survey_scenario/scenario_tools/compute_take_up_rate.py
leximpact_survey_scenario/scenario_tools/helpers_survey_scenario.py
leximpact_survey_scenario/scenario_tools/inflation_calibration_values.py
leximpact_survey_scenario/scenario_tools/inflator.py
leximpact_survey_scenario/scenario_tools/input_variables_list.py
leximpact_survey_scenario/scenario_tools/plot.py
leximpact_survey_scenario-1.3.1.dist-info/LICENSE
leximpact_survey_scenario-1.3.1.dist-info/LICENSE.md
leximpact_survey_scenario-1.3.1.dist-info/METADATA
leximpact_survey_scenario-1.3.1.dist-info/WHEEL
leximpact_survey_scenario-1.3.1.dist-info/RECORD
