Metadata-Version: 2.1
Name: leximpact-survey-scenario
Version: 1.3.1
Summary: OpenFisca Survey Scenario for LexImpact
License: LGPLv3
Author: LexImpact
Author-email: leximpact@an.fr
Requires-Python: >=3.9,<4.0
Classifier: License :: Other/Proprietary License
Classifier: Programming Language :: Python :: 3
Classifier: Programming Language :: Python :: 3.9
Classifier: Programming Language :: Python :: 3.10
Classifier: Programming Language :: Python :: 3.11
Classifier: Programming Language :: Python :: 3.12
Requires-Dist: OpenFisca-France-Data (>=3.0.1,<4.0.0)
Requires-Dist: ipykernel (>=6.24.0,<7.0.0)
Requires-Dist: pytest-asyncio (>=0.21.1,<0.22.0)
Requires-Dist: python-decouple (>=3.8,<4.0)
Requires-Dist: scikit-learn (>=1.3.0,<2.0.0)
